socialsync/__init__.py
socialsync/analytics.py
socialsync/api.py
socialsync/auth.py
socialsync/backend_integration.py
socialsync/exceptions.py
socialsync/logging_handler.py
socialsync/machine_len_utils.py
socialsync/main_code_checker.py
socialsync/sync_manager.py
socialsync/utils.py
ssync-1.0.1.dev0.dist-info/LICENSE.md
ssync-1.0.1.dev0.dist-info/METADATA
ssync-1.0.1.dev0.dist-info/WHEEL
ssync-1.0.1.dev0.dist-info/top_level.txt
ssync-1.0.1.dev0.dist-info/RECORD
