Metadata-Version: 2.1
Name: ssync
Version: 1.0.1.dev0
Summary: A powerful Python library for automating interactions with social media platforms and integrating them with backend systems.
Home-page: 
Author: Mark
Author-email: socialsync.software@outlook.com
Classifier: Programming Language :: Python :: 3
Classifier: License :: OSI Approved :: MIT License
Classifier: Operating System :: OS Independent
Requires-Python: >=3.8
License-File: LICENSE.md
Requires-Dist: requests>=2.28.1
Requires-Dist: hashlib>=1.0.1
Requires-Dist: typing-extensions>=4.0.0
Requires-Dist: pytest>=7.0.0
Requires-Dist: flake8>=5.0.0
Requires-Dist: black>=23.0.0
Requires-Dist: pandas>=1.3.0
Requires-Dist: aiohttp>=3.8.0
Requires-Dist: cryptography>=3.0.0
